<?xml version = '1.0' encoding = 'UTF-8'?>
<Relation class="oracle.dbtools.crest.model.design.logical.Relation" name="Cliente_Credenciales_FK" directorySegmentName="seg_0" id="D6B5BD55-5A25-4962-4765-722DBE2EAA14">
<createdBy>Gibafenrir</createdBy>
<createdTime>2021-04-16 00:23:06 UTC</createdTime>
<generatorID>EAF2565E-FB2C-6723-DAE8-5B6A1B89872E</generatorID>
<ownerDesignName>ER</ownerDesignName>
<engineerTo>
<item key="0E13A7B1-BC82-0E9A-8456-19BFA79E40BD" value="true"/>
</engineerTo>
<sourcePk>AE6AB859-B604-0382-DD1D-20749B3E1D03</sourcePk>
<identifying>false</identifying>
<optionalSource>true</optionalSource>
<optionalTarget>false</optionalTarget>
<sourceCardinality>1</sourceCardinality>
<sourceEntity>35A73D43-AC93-FF18-15D8-D762E2B79043</sourceEntity>
<targetCardinalityString>*</targetCardinalityString>
<targetEntity>7A092AEF-F0FA-B6DC-7615-5C2418DACFAA</targetEntity>
<transferable>true</transferable>
<deleteRule>NO ACTION</deleteRule>
</Relation>